ipfabric_snow/apps/env_setup.py
ipfabric_snow/apps/sync_devices.py
ipfabric_snow/main.py
ipfabric_snow/utils/env_manager.py
ipfabric_snow/utils/etl.py
ipfabric_snow/utils/logger.py
ipfabric_snow/utils/servicenow_client.py
ipfabric_snow-0.1.0b16.dist-info/METADATA
ipfabric_snow-0.1.0b16.dist-info/WHEEL
ipfabric_snow-0.1.0b16.dist-info/entry_points.txt
ipfabric_snow-0.1.0b16.dist-info/RECORD
