Metadata-Version: 2.1
Name: ipfabric-snow
Version: 0.1.0b16
Summary: Integration with ServiceNow and IP Fabric
License: MIT
Author: Cristian Cordero
Author-email: cristian.cordero@ipfabric.io
Requires-Python: >=3.9,<4.0
Classifier: License :: OSI Approved :: MIT License
Classifier: Programming Language :: Python :: 3
Classifier: Programming Language :: Python :: 3.9
Classifier: Programming Language :: Python :: 3.10
Classifier: Programming Language :: Python :: 3.11
Classifier: Programming Language :: Python :: 3.12
Classifier: Programming Language :: Python :: 3.13
Requires-Dist: ipfabric (>=7.0.0b3)
Requires-Dist: loguru (>=0.7.2,<0.8.0)
Requires-Dist: rich (>=13.8.1,<14.0.0)
Requires-Dist: typer[all] (>=0.9.0,<0.10.0)
